euslint/__init__.py
euslint/lint.py
euslint/parse.py
euslint/test.py
euslint-1.0.2.data/scripts/euslint
euslint-1.0.2.dist-info/LICENSE
euslint-1.0.2.dist-info/METADATA
euslint-1.0.2.dist-info/WHEEL
euslint-1.0.2.dist-info/top_level.txt
euslint-1.0.2.dist-info/RECORD
