Metadata-Version: 2.1
Name: euslint
Version: 1.0.2
Summary: Linter for euslisp
Home-page: https://github.com/knorth55/euslint
Author: Shingo Kitagawa
Author-email: shingogo.5511@gmail.com
License: MIT
Keywords: linter
Platform: UNKNOWN
Requires-Dist: argparse
